codestare/async_utils/__init__.py
codestare/async_utils/descriptor.py
codestare/async_utils/helper.py
codestare/async_utils/nursery.py
codestare/async_utils/py.typed
codestare/async_utils/type_vars.py
codestare/async_utils/wrapper.py
codestare_async_utils-0.2.0.dist-info/LICENSE.rst
codestare_async_utils-0.2.0.dist-info/METADATA
codestare_async_utils-0.2.0.dist-info/WHEEL
codestare_async_utils-0.2.0.dist-info/top_level.txt
codestare_async_utils-0.2.0.dist-info/RECORD
