Metadata-Version: 2.1
Name: codestare-async-utils
Version: 0.2.0
Summary: "Utility modules for async development"
Home-page: https://github.com/saggitar/codestare-async-utils
Author: Maximilian Schmidt
Author-email: ga97lul@mytum.de
Keywords: async
Classifier: Programming Language :: Python :: 3
Requires-Python: >=3.7
License-File: LICENSE.rst
Requires-Dist: backports.cached-property ; python_version <= "3.7"
Requires-Dist: typing-extensions ; python_version <= "3.7"
Provides-Extra: test
Requires-Dist: pytest ; extra == 'test'
Requires-Dist: pytest-asyncio ; extra == 'test'
